{
    "name": "Province",
    "fields": [
        {
            "fieldName": "provinceCode",
            "fieldType": "String",
            "fieldValidateRules": [
                "maxlength"
            ],
            "fieldValidateRulesMaxlength": 10
        },
        {
            "fieldName": "provinceName",
            "fieldType": "String",
            "fieldValidateRules": [
                "maxlength"
            ],
            "fieldValidateRulesMaxlength": 60
        }
    ],
    "relationships": [
        {
            "relationshipType": "one-to-many",
            "otherEntityName": "city",
            "otherEntityRelationshipName": "province",
            "relationshipName": "city"
        },
        {
            "relationshipType": "one-to-many",
            "otherEntityName": "investorAddress",
            "otherEntityRelationshipName": "province",
            "relationshipName": "investorAddress"
        },
        {
            "relationshipType": "many-to-one",
            "otherEntityName": "country",
            "otherEntityRelationshipName": "province",
            "relationshipName": "country",
            "otherEntityField": "id"
        }
    ],
    "changelogDate": "20191015060743",
    "entityTableName": "province",
    "dto": "mapstruct",
    "pagination": "no",
    "service": "serviceImpl",
    "jpaMetamodelFiltering": false,
    "fluentMethods": true,
    "readOnly": false,
    "clientRootFolder": "",
    "applications": "*",
    "angularJSSuffix": "mySuffix"
}